{
  "fixtures": [
    {
      "match": {
        "endpoint": "fal",
        "userMessage": "Steady handheld drifts slowly forward. Scarlett turns her head gradually away from camera to face the open ocean, her smile softening to a small private expression as wind sweeps hair across her face. A wave breaks, sending foam around her bare feet.\nLight breeze stirs the hem of her skirt and canvas tote.\n\nocean waves and gentle wind. wave breaking at feet, hair and fabric fluttering.\n\nSingle continuous shot, no cuts. Avoid jitter and bent limbs.",
        "model": "bytedance/seedance-2.0/enterprise/v2/image-to-video",
        "turnIndex": 0,
        "hasToolResult": false
      },
      "response": {
        "json": {
          "video": {
            "url": "https://v3b.fal.media/files/b/0aa07d25/5hYUEzBvwA1xR33GyFA7Q_video.mp4",
            "content_type": "video/mp4",
            "file_name": "video.mp4",
            "file_size": 2766453
          },
          "seed": 2060557651
        },
        "status": 200
      }
    }
  ]
}
